{
  "main": {
    "id": "76d3d372c70d655a",
    "type": "split",
    "children": [
      {
        "id": "1a89094d963de093",
        "type": "tabs",
        "children": [
          {
            "id": "086f549d2c5574b0",
            "type": "leaf",
            "state": {
              "type": "markdown",
              "state": {
                "file": "Utility Tools.md",
                "mode": "preview",
                "source": false
              },
              "icon": "lucide-file",
              "title": "Utility Tools"
            }
          }
        ]
      }
    ],
    "direction": "vertical"
  },
  "left": {
    "id": "e9afcd203e5c949f",
    "type": "split",
    "children": [
      {
        "id": "78b00408cf8ec6f1",
        "type": "tabs",
        "children": [
          {
            "id": "1ad70181c6f8c0e6",
            "type": "leaf",
            "state": {
              "type": "file-explorer",
              "state": {
                "sortOrder": "alphabetical",
                "autoReveal": false
              },
              "icon": "lucide-folder-closed",
              "title": "Files"
            }
          },
          {
            "id": "d362671d0994ba72",
            "type": "leaf",
            "state": {
              "type": "search",
              "state": {
                "query": "",
                "matchingCase": false,
                "explainSearch": false,
                "collapseAll": false,
                "extraContext": false,
                "sortOrder": "alphabetical"
              },
              "icon": "lucide-search",
              "title": "Search"
            }
          },
          {
            "id": "ce95de6b03c97128",
            "type": "leaf",
            "state": {
              "type": "bookmarks",
              "state": {},
              "icon": "lucide-bookmark",
              "title": "Bookmarks"
            }
          }
        ]
      }
    ],
    "direction": "horizontal",
    "width": 300
  },
  "right": {
    "id": "ef628e923b2d10ea",
    "type": "split",
    "children": [
      {
        "id": "cc259398088d0b89",
        "type": "tabs",
        "children": [
          {
            "id": "e2456a5b6db55537",
            "type": "leaf",
            "state": {
              "type": "backlink",
              "state": {
                "file": "Utility Tools.md",
                "collapseAll": false,
                "extraContext": false,
                "sortOrder": "alphabetical",
                "showSearch": false,
                "searchQuery": "",
                "backlinkCollapsed": false,
                "unlinkedCollapsed": true
              },
              "icon": "links-coming-in",
              "title": "Backlinks for Utility Tools"
            }
          },
          {
            "id": "1d4425258d6e76f2",
            "type": "leaf",
            "state": {
              "type": "outgoing-link",
              "state": {
                "file": "Utility Tools.md",
                "linksCollapsed": false,
                "unlinkedCollapsed": true
              },
              "icon": "links-going-out",
              "title": "Outgoing links from Utility Tools"
            }
          },
          {
            "id": "774399b18ba86255",
            "type": "leaf",
            "state": {
              "type": "tag",
              "state": {
                "sortOrder": "frequency",
                "useHierarchy": true,
                "showSearch": false,
                "searchQuery": ""
              },
              "icon": "lucide-tags",
              "title": "Tags"
            }
          },
          {
            "id": "a73d99c0f81fb2c6",
            "type": "leaf",
            "state": {
              "type": "outline",
              "state": {
                "file": "Utility Tools.md",
                "followCursor": false,
                "showSearch": false,
                "searchQuery": ""
              },
              "icon": "lucide-list",
              "title": "Outline of Utility Tools"
            }
          }
        ]
      }
    ],
    "direction": "horizontal",
    "width": 300,
    "collapsed": true
  },
  "left-ribbon": {
    "hiddenItems": {
      "switcher:Open quick switcher": false,
      "graph:Open graph view": false,
      "canvas:Create new canvas": false,
      "daily-notes:Open today's daily note": false,
      "templates:Insert template": false,
      "command-palette:Open command palette": false,
      "bases:Create new base": false
    }
  },
  "active": "086f549d2c5574b0",
  "lastOpenFiles": [
    "The Inner Board .md"
  ]
}